courier.py
setup.py
courier_py.egg-info/PKG-INFO
courier_py.egg-info/SOURCES.txt
courier_py.egg-info/dependency_links.txt
courier_py.egg-info/top_level.txt