Metadata-Version: 1.0
Name: courier-py
Version: 0.1
Summary: Courier (A SMS Broker) Client for Python
Home-page: https://github.com/toraysoft/courier-py
Author: jeff kit
Author-email: jeff@toraysoft.com
License: UNKNOWN
Platform: UNKNOWN
